sprayhound/__init__.py
sprayhound/core.py
sprayhound/modules/__init__.py
sprayhound/modules/credential.py
sprayhound/modules/ldapconnection.py
sprayhound/modules/logger.py
sprayhound/modules/neo4jconnection.py
sprayhound/utils/__init__.py
sprayhound/utils/defines.py
sprayhound/utils/utils.py
sprayhound-0.0.4.dist-info/LICENSE
sprayhound-0.0.4.dist-info/METADATA
sprayhound-0.0.4.dist-info/WHEEL
sprayhound-0.0.4.dist-info/entry_points.txt
sprayhound-0.0.4.dist-info/top_level.txt
sprayhound-0.0.4.dist-info/zip-safe
sprayhound-0.0.4.dist-info/RECORD
