Metadata-Version: 2.1
Name: sprayhound
Version: 0.0.4
Summary: Password spraying with BloodHound integration
Home-page: https://github.com/hackanddo/sprayhound
Author: pixis
Author-email: pixis@hackndo.com
License: MIT
Classifier: Programming Language :: Python :: 3.6
Classifier: Programming Language :: Python :: 3.7
Classifier: Programming Language :: Python :: 3.8
Classifier: Programming Language :: Python :: 3.9
Classifier: Programming Language :: Python :: 3.10
Classifier: Programming Language :: Python :: 3.11
Classifier: License :: OSI Approved :: MIT License
Classifier: Operating System :: OS Independent
Requires-Python: >=3.6
License-File: LICENSE
Requires-Dist: neo4j
Requires-Dist: ldap3
